{
    "en": {
        "name": "English",
        "BTN_SAVE": "Save",
        "BTN_INIT": "Initialize",
        "LBL_TITLE": "Animal Crossing Turnip Price Predictor",
        "LBL_SELLING_PRICE": "Selling Price",
        "LBL_MONDAY": "Mon",
        "LBL_TUESDAY": "Tue",
        "LBL_WEDNESDAY": "Wed",
        "LBL_THURSDAY": "Thu",
        "LBL_FRIDAY": "Fri",
        "LBL_SATURDAY": "Sat",
        "LBL_AM": "AM",
        "LBL_PM": "PM",
        "MSG_SAVE_SUCCESSFULLY": "Save successfully!",
        "MSG_INIT_SUCCESSFULLY": "Initialize Successfully!"
    },
    "ko": {
        "name": "한국어",
        "BTN_SAVE": "저장",
        "BTN_INIT": "초기화",
        "LBL_TITLE": "동물의숲 무가격 예측기",
        "LBL_SELLING_PRICE": "판매가",
        "LBL_MONDAY": "월요일",
        "LBL_TUESDAY": "화요일",
        "LBL_WEDNESDAY": "수요일",
        "LBL_THURSDAY": "목요일",
        "LBL_FRIDAY": "금요일",
        "LBL_SATURDAY": "토요일",
        "LBL_AM": "오전",
        "LBL_PM": "오후",
        "MSG_SAVE_SUCCESSFULLY": "저장에 성공했습니다!",
        "MSG_INIT_SUCCESSFULLY": "초기화에 성공했습니다!"
    }
}